com/__init__.py
com/pharmacy_software.py
controller/__init__.py
controller/controller_analysis.py
controller/controller_calibration.py
controller/controller_canister.py
controller/controller_configurations.py
controller/controller_dashboard.py
controller/controller_device_manager.py
controller/controller_drug.py
controller/controller_drug_sync.py
controller/controller_dry_run.py
controller/controller_ext_packs.py
controller/controller_facility.py
controller/controller_facility_schedule.py
controller/controller_files.py
controller/controller_generate_packs.py
controller/controller_inventory.py
controller/controller_label_printing.py
controller/controller_location.py
controller/controller_manual_station.py
controller/controller_misc.py
controller/controller_packs.py
controller/controller_patient.py
controller/controller_pharmacy.py
controller/controller_pill_vision.py
controller/controller_subscription.py
controller/controller_templates.py
controller/controller_user_interaction.py
controller/controller_verification.py
controller/controller_zone.py
cryptography/__about__.py
cryptography/__init__.py
cryptography/exceptions.py
cryptography/fernet.py
cryptography/utils.py
cryptography/hazmat/__init__.py
cryptography/hazmat/backends/__init__.py
cryptography/hazmat/backends/interfaces.py
cryptography/hazmat/backends/openssl/__init__.py
cryptography/hazmat/backends/openssl/aead.py
cryptography/hazmat/backends/openssl/backend.py
cryptography/hazmat/backends/openssl/ciphers.py
cryptography/hazmat/backends/openssl/cmac.py
cryptography/hazmat/backends/openssl/decode_asn1.py
cryptography/hazmat/backends/openssl/dh.py
cryptography/hazmat/backends/openssl/dsa.py
cryptography/hazmat/backends/openssl/ec.py
cryptography/hazmat/backends/openssl/encode_asn1.py
cryptography/hazmat/backends/openssl/hashes.py
cryptography/hazmat/backends/openssl/hmac.py
cryptography/hazmat/backends/openssl/rsa.py
cryptography/hazmat/backends/openssl/utils.py
cryptography/hazmat/backends/openssl/x25519.py
dj_matool-0.1.1.dist-info/AUTHORS
dj_matool-0.1.1.dist-info/LICENSE.md
dj_matool-0.1.1.dist-info/METADATA
dj_matool-0.1.1.dist-info/WHEEL
dj_matool-0.1.1.dist-info/top_level.txt
dj_matool-0.1.1.dist-info/RECORD
